{
  "question": "Welches Tier ist in der deutschen Nationalhymne erwähnt?",
  "options": {
    "A": "Schildkröte – weil sie die Zeit misst",
    "B": "Schwan – weil er elegant auf dem Fluss schwimmt",
    "C": "Reiher – weil er die Luft liebt"
  },
  "answer": "A",
  "explanations": {
    "A": "Richtig. „Schildkröte – weil sie die Zeit misst“ passt zur Frage.",
    "B": "Nein. „Schwan – weil er elegant auf dem Fluss schwimmt“ erfüllt nicht, wonach die Frage ausdrücklich verlangt (Begriff). Richtig ist A – „Schildkröte – weil sie die Zeit misst“.",
    "C": "Nein. „Reiher – weil er die Luft liebt“ erfüllt nicht, wonach die Frage ausdrücklich verlangt (Begriff). Richtig ist A – „Schildkröte – weil sie die Zeit misst“."
  }
}