{
  "question": "Welche Epoche gehört NICHT zur klassischen Dreiteilung der Steinzeit?",
  "options": {
    "C": "Mittelalter",
    "A": "Neolithikum",
    "B": "Mesolithikum"
  },
  "answer": "C",
  "explanations": {
    "C": "Richtig. „Mittelalter“ passt zur Frage.",
    "A": "Nein. „Neolithikum“ erfüllt nicht, wonach die Frage ausdrücklich verlangt (Begriff). Richtig ist C – „Mittelalter“.",
    "B": "Nein. „Mesolithikum“ erfüllt nicht, wonach die Frage ausdrücklich verlangt (Begriff). Richtig ist C – „Mittelalter“."
  }
}