{
  "question": "Welche Sportart nutzt traditionell kein rundes Spielgerät?",
  "options": {
    "C": "American Football",
    "A": "Basketball",
    "B": "Fußball"
  },
  "answer": "C",
  "explanations": {
    "C": "Richtig. „American Football“ passt zur Frage.",
    "A": "Nein. „Basketball“ erfüllt nicht, wonach die Frage ausdrücklich verlangt (Begriff). Richtig ist C – „American Football“.",
    "B": "Nein. „Fußball“ erfüllt nicht, wonach die Frage ausdrücklich verlangt (Begriff). Richtig ist C – „American Football“."
  }
}