{
  "question": "Wofür steht die Abkürzung 'GPU'?",
  "options": {
    "A": "Graphics Processing Unit",
    "B": "General Power Unit",
    "C": "Global Processing Utility"
  },
  "answer": "A",
  "explanations": {
    "A": "Richtig. „Graphics Processing Unit“ passt zur Frage.",
    "B": "Nein. „General Power Unit“ erfüllt nicht, wonach die Frage ausdrücklich verlangt (Begriff). Richtig ist A – „Graphics Processing Unit“.",
    "C": "Nein. „Global Processing Utility“ erfüllt nicht, wonach die Frage ausdrücklich verlangt (Begriff). Richtig ist A – „Graphics Processing Unit“."
  }
}