{
  "question": "Welche Kurzbeschreibung passt am besten zu Castlevania?",
  "options": {
    "B": "Vampirjagd, Peitsche, Dracula",
    "A": "Städtebau, Zonen & Strom",
    "C": "Labyrinthe sprengen"
  },
  "answer": "B",
  "explanations": {
    "B": "Richtig. „Vampirjagd, Peitsche, Dracula“ passt zur Frage.",
    "A": "Nein. „Städtebau, Zonen & Strom“ erfüllt nicht, wonach die Frage ausdrücklich verlangt (Begriff). Richtig ist B – „Vampirjagd, Peitsche, Dracula“.",
    "C": "Nein. „Labyrinthe sprengen“ erfüllt nicht, wonach die Frage ausdrücklich verlangt (Begriff). Richtig ist B – „Vampirjagd, Peitsche, Dracula“."
  }
}